{"config": {"view": {"continuousWidth": 300, "continuousHeight": 300}, "locale": {"number": {"decimal": ",", "thousands": ".", "grouping": [3], "currency": ["", "\u00a0\u20ac"]}}, "title": {"dx": 30, "dy": -15, "fontSize": 15}}, "data": {"name": "data-2b82c2e54acbb3b71ef980bae56e4bb3"}, "facet": {"column": {"field": "seg2", "header": {"labelFontSize": 15}, "sort": {"field": "order"}, "title": null, "type": "nominal"}, "row": {"field": "row", "header": {"labels": false}, "sort": {"field": "order"}, "title": null, "type": "nominal"}}, "spec": {"layer": [{"mark": {"type": "errorbar", "ticks": {"width": 10}}, "encoding": {"tooltip": {"value": null}, "y": {"axis": {"format": "%", "labelFontSize": 11}, "field": "lower", "title": null, "type": "quantitative"}, "y2": {"field": "upper"}}}, {"mark": {"type": "line", "point": {"size": 50}}, "encoding": {"tooltip": [{"field": "seg1", "title": "Grupo", "type": "nominal"}, {"field": "prop", "format": ".2%", "title": "Estimaci\u00f3n", "type": "quantitative"}, {"field": "lower", "format": ".2%", "title": "L\u00edmite inferior", "type": "quantitative"}, {"field": "upper", "format": ".2%", "title": "L\u00edmite superior", "type": "quantitative"}], "y": {"axis": {"format": "%", "labelFontSize": 11}, "field": "prop", "title": null, "type": "quantitative"}}, "name": "view_3284"}], "encoding": {"color": {"field": "seg1", "legend": {"labelFontSize": 12, "symbolSize": 400}, "sort": {"field": "order"}, "title": null, "type": "nominal"}, "x": {"axis": {"labelAngle": 0, "labelFontSize": 11}, "field": "M", "sort": {"field": "order"}, "title": null, "type": "nominal"}, "xOffset": {"field": "seg1", "scale": {"paddingOuter": 0.5}, "sort": {"field": "order"}, "type": "nominal"}}, "height": 175, "width": {"step": 45, "for": "position"}}, "params": [{"name": "param_4326", "select": {"type": "interval", "encodings": ["x", "y"]}, "bind": "scales", "views": ["view_3284"]}], "resolve": {"axis": {"x": "independent", "y": "independent"}, "scale": {"xOffset": "independent"}}, "title": {"text": ["Poblaci\u00f3n con diagn\u00f3stico de incontinencia urinaria por edici\u00f3n, sexo y clase social (porcentajes e intervalos de confianza al 95%)"], "subtitle": "Fuente: Encuesta Andaluza de Salud (adultos). C\u00f3digo de variable: P1432"}, "transform": [{"calculate": "datum.seg1 == 'Total'", "as": "row"}, {"filter": "true == true"}], "$schema": "https://vega.github.io/schema/vega-lite/v5.17.0.json", "datasets": {"data-2b82c2e54acbb3b71ef980bae56e4bb3": [{"M": "2007", "seg1": "Hombre", "seg2": "Grupo I y II", "prop": 0.009405312242782685, "lower": 0.0020742845807972415, "upper": 0.02295548537761183, "n": 4, "N": 4456, "order": 0}, {"M": "2007", "seg1": "Hombre", "seg2": "Grupo III", "prop": 0.012466834342666896, "lower": 0.004772436453211594, "upper": 0.02776719572624114, "n": 5, "N": 4575, "order": 1}, {"M": "2007", "seg1": "Hombre", "seg2": "Grupo IV y V", "prop": 0.011387503491376827, "lower": 0.003480705879336062, "upper": 0.023090230946649824, "n": 6, "N": 6176, "order": 2}, {"M": "2007", "seg1": "Hombre", "seg2": "Grupo VI", "prop": 0.012818184833037373, "lower": 0.007679345590214323, "upper": 0.02049910044097072, "n": 17, "N": 15873, "order": 3}, {"M": "2007", "seg1": "Hombre", "seg2": "Grupo VII", "prop": 0.013815954593473293, "lower": 0.005230848846821198, "upper": 0.027973190929509173, "n": 5, "N": 4843, "order": 4}, {"M": "2007", "seg1": "Hombre", "seg2": "No ha trabajado", "prop": 0.0, "lower": null, "upper": null, "n": 0, "N": 0, "order": 5}, {"M": "2007", "seg1": "Hombre", "seg2": "Total", "prop": 0.010985122098908036, "lower": 0.007901499995593064, "upper": 0.015176097841281471, "n": 37, "N": 35923, "order": 6}, {"M": "2007", "seg1": "Mujer", "seg2": "Grupo I y II", "prop": 0.002792193331908836, "lower": 0.0, "upper": 0.014159688132406624, "n": 1, "N": 856, "order": 7}, {"M": "2007", "seg1": "Mujer", "seg2": "Grupo III", "prop": 0.011218293188342606, "lower": 0.0027826998300353035, "upper": 0.029804219361773326, "n": 4, "N": 4172, "order": 8}, {"M": "2007", "seg1": "Mujer", "seg2": "Grupo IV y V", "prop": 0.013757502506665227, "lower": 0.0, "upper": 0.04811581139680332, "n": 2, "N": 2308, "order": 9}, {"M": "2007", "seg1": "Mujer", "seg2": "Grupo VI", "prop": 0.008262941587398397, "lower": 0.00284627906487163, "upper": 0.01635954799663402, "n": 6, "N": 5902, "order": 10}, {"M": "2007", "seg1": "Mujer", "seg2": "Grupo VII", "prop": 0.01941746653074443, "lower": 0.009479596771256206, "upper": 0.035166017319573785, "n": 11, "N": 11044, "order": 11}, {"M": "2007", "seg1": "Mujer", "seg2": "No ha trabajado", "prop": 0.02114619563314401, "lower": 0.013547257144656804, "upper": 0.030536669875484444, "n": 24, "N": 26407, "order": 12}, {"M": "2007", "seg1": "Mujer", "seg2": "Total", "prop": 0.015004953787382319, "lower": 0.01086923635779567, "upper": 0.019371871729707134, "n": 48, "N": 50689, "order": 13}, {"M": "2007", "seg1": "Total", "seg2": "Grupo I y II", "prop": 0.006806688216132706, "lower": 0.002324359954663161, "upper": 0.01575050048473231, "n": 5, "N": 5312, "order": 14}, {"M": "2007", "seg1": "Total", "seg2": "Grupo III", "prop": 0.011838397399640354, "lower": 0.005313628001271709, "upper": 0.021248741259571265, "n": 9, "N": 8746, "order": 15}, {"M": "2007", "seg1": "Total", "seg2": "Grupo IV y V", "prop": 0.011947429135672996, "lower": 0.0053881763219389475, "upper": 0.02340162407848748, "n": 8, "N": 8485, "order": 16}, {"M": "2007", "seg1": "Total", "seg2": "Grupo VI", "prop": 0.011151837118341657, "lower": 0.007522037330932057, "upper": 0.01682588445040111, "n": 23, "N": 21775, "order": 17}, {"M": "2007", "seg1": "Total", "seg2": "Grupo VII", "prop": 0.017281467031495468, "lower": 0.009607682940443113, "upper": 0.02784461888486049, "n": 16, "N": 15887, "order": 18}, {"M": "2007", "seg1": "Total", "seg2": "No ha trabajado", "prop": 0.0170699392283928, "lower": 0.011049696236251839, "upper": 0.024558278992574324, "n": 24, "N": 26407, "order": 19}, {"M": "2007", "seg1": "Total", "seg2": "Total", "prop": 0.013027668516859875, "lower": 0.010393373748183481, "upper": 0.016374721605015165, "n": 85, "N": 86612, "order": 20}, {"M": "2012", "seg1": "Hombre", "seg2": "Grupo I y II", "prop": 0.0021821938859747244, "lower": 0.0, "upper": 0.010846991739264131, "n": 1, "N": 954, "order": 21}, {"M": "2012", "seg1": "Hombre", "seg2": "Grupo III", "prop": 0.0024602959273180756, "lower": 0.0, "upper": 0.01473158121956321, "n": 1, "N": 1030, "order": 22}, {"M": "2012", "seg1": "Hombre", "seg2": "Grupo IV y V", "prop": 0.011864235623898416, "lower": 0.0048887675924167585, "upper": 0.02697848752895221, "n": 6, "N": 7468, "order": 23}, {"M": "2012", "seg1": "Hombre", "seg2": "Grupo VI", "prop": 0.008705877695472222, "lower": 0.003567661544904764, "upper": 0.01673685222182187, "n": 9, "N": 10090, "order": 24}, {"M": "2012", "seg1": "Hombre", "seg2": "Grupo VII", "prop": 0.006100755852512872, "lower": 0.0019776263720265863, "upper": 0.016379700217327882, "n": 3, "N": 3115, "order": 25}, {"M": "2012", "seg1": "Hombre", "seg2": "No ha trabajado", "prop": 0.0, "lower": null, "upper": null, "n": 0, "N": 0, "order": 26}, {"M": "2012", "seg1": "Hombre", "seg2": "Total", "prop": 0.00662121026512831, "lower": 0.003887301481876801, "upper": 0.010566132117985872, "n": 20, "N": 22657, "order": 27}, {"M": "2012", "seg1": "Mujer", "seg2": "Grupo I y II", "prop": 0.009979815923619363, "lower": 0.003043819722030381, "upper": 0.026113398533377588, "n": 3, "N": 3138, "order": 28}, {"M": "2012", "seg1": "Mujer", "seg2": "Grupo III", "prop": 0.0, "lower": null, "upper": null, "n": 0, "N": 0, "order": 29}, {"M": "2012", "seg1": "Mujer", "seg2": "Grupo IV y V", "prop": 0.011581897398687358, "lower": 0.003614874651451345, "upper": 0.0313588105353029, "n": 3, "N": 3013, "order": 30}, {"M": "2012", "seg1": "Mujer", "seg2": "Grupo VI", "prop": 0.006703070686682744, "lower": 0.0025416299547637343, "upper": 0.014634775069895928, "n": 5, "N": 5126, "order": 31}, {"M": "2012", "seg1": "Mujer", "seg2": "Grupo VII", "prop": 0.028124785563287565, "lower": 0.016949730074788637, "upper": 0.040942626108923574, "n": 20, "N": 21382, "order": 32}, {"M": "2012", "seg1": "Mujer", "seg2": "No ha trabajado", "prop": 0.022768273980154925, "lower": 0.01451385049849471, "upper": 0.033803425027435136, "n": 22, "N": 25233, "order": 33}, {"M": "2012", "seg1": "Mujer", "seg2": "Total", "prop": 0.016326757351458353, "lower": 0.01238249115060881, "upper": 0.021378777441022723, "n": 53, "N": 57892, "order": 34}, {"M": "2012", "seg1": "Total", "seg2": "Grupo I y II", "prop": 0.0054442791404635486, "lower": 0.0013807332150075778, "upper": 0.013801499573247864, "n": 4, "N": 4092, "order": 35}, {"M": "2012", "seg1": "Total", "seg2": "Grupo III", "prop": 0.0013614607309947399, "lower": 0.0, "upper": 0.006830998483267814, "n": 1, "N": 1030, "order": 36}, {"M": "2012", "seg1": "Total", "seg2": "Grupo IV y V", "prop": 0.011781671455096288, "lower": 0.0057888621781320045, "upper": 0.022494826711085186, "n": 9, "N": 10480, "order": 37}, {"M": "2012", "seg1": "Total", "seg2": "Grupo VI", "prop": 0.007909721363772625, "lower": 0.004284795210585429, "upper": 0.013209584640925505, "n": 14, "N": 15216, "order": 38}, {"M": "2012", "seg1": "Total", "seg2": "Grupo VII", "prop": 0.01927602033530818, "lower": 0.012276113654842085, "upper": 0.02837410186702721, "n": 23, "N": 24497, "order": 39}, {"M": "2012", "seg1": "Total", "seg2": "No ha trabajado", "prop": 0.018349444682517355, "lower": 0.01201989482032313, "upper": 0.027859440984360592, "n": 22, "N": 25233, "order": 40}, {"M": "2012", "seg1": "Total", "seg2": "Total", "prop": 0.011560273135335654, "lower": 0.00924243040540822, "upper": 0.014532922034434233, "n": 73, "N": 80549, "order": 41}, {"M": "2016", "seg1": "Hombre", "seg2": "Grupo I y II", "prop": 0.004298369422844355, "lower": 0.0, "upper": 0.013059203985190252, "n": 2, "N": 1844, "order": 42}, {"M": "2016", "seg1": "Hombre", "seg2": "Grupo III", "prop": 0.004749305595128802, "lower": 0.0, "upper": 0.01667774726962033, "n": 2, "N": 1792, "order": 43}, {"M": "2016", "seg1": "Hombre", "seg2": "Grupo IV y V", "prop": 0.006510585960011546, "lower": 0.001498261188010813, "upper": 0.019541666855365934, "n": 3, "N": 3398, "order": 44}, {"M": "2016", "seg1": "Hombre", "seg2": "Grupo VI", "prop": 0.003789815709545563, "lower": 0.0015123627019378283, "upper": 0.008407230855967836, "n": 5, "N": 4357, "order": 45}, {"M": "2016", "seg1": "Hombre", "seg2": "Grupo VII", "prop": 0.009868075622225487, "lower": 0.003999138358794104, "upper": 0.01790293913379226, "n": 7, "N": 6125, "order": 46}, {"M": "2016", "seg1": "Hombre", "seg2": "No ha trabajado", "prop": 0.0, "lower": null, "upper": null, "n": 0, "N": 0, "order": 47}, {"M": "2016", "seg1": "Hombre", "seg2": "Total", "prop": 0.005173494987494256, "lower": 0.003163532952786527, "upper": 0.008132144582367344, "n": 19, "N": 17516, "order": 48}, {"M": "2016", "seg1": "Mujer", "seg2": "Grupo I y II", "prop": 0.007123917948186808, "lower": 0.0, "upper": 0.02175137009652317, "n": 2, "N": 2472, "order": 49}, {"M": "2016", "seg1": "Mujer", "seg2": "Grupo III", "prop": 0.012164312676661841, "lower": 0.0028283923746001654, "upper": 0.036808765179134235, "n": 3, "N": 4528, "order": 50}, {"M": "2016", "seg1": "Mujer", "seg2": "Grupo IV y V", "prop": 0.013919746685424164, "lower": 0.0, "upper": 0.04332357556040595, "n": 2, "N": 2312, "order": 51}, {"M": "2016", "seg1": "Mujer", "seg2": "Grupo VI", "prop": 0.011135326724068315, "lower": 0.005010516267056831, "upper": 0.020248839854608198, "n": 8, "N": 9196, "order": 52}, {"M": "2016", "seg1": "Mujer", "seg2": "Grupo VII", "prop": 0.01035902264393737, "lower": 0.004567977505279081, "upper": 0.02095990390948711, "n": 7, "N": 7647, "order": 53}, {"M": "2016", "seg1": "Mujer", "seg2": "No ha trabajado", "prop": 0.02320874188023624, "lower": 0.01475623080163421, "upper": 0.033891235710274525, "n": 22, "N": 25112, "order": 54}, {"M": "2016", "seg1": "Mujer", "seg2": "Total", "prop": 0.014517387613413535, "lower": 0.010498296350112813, "upper": 0.01916877904478211, "n": 44, "N": 51270, "order": 55}, {"M": "2016", "seg1": "Total", "seg2": "Grupo I y II", "prop": 0.0055618164042337175, "lower": 0.0012784911709710072, "upper": 0.014164560400275496, "n": 4, "N": 4317, "order": 56}, {"M": "2016", "seg1": "Total", "seg2": "Grupo III", "prop": 0.008432304863307281, "lower": 0.0029480064152342857, "upper": 0.021372883505054136, "n": 5, "N": 6320, "order": 57}, {"M": "2016", "seg1": "Total", "seg2": "Grupo IV y V", "prop": 0.008299488969012218, "lower": 0.003271557846155457, "upper": 0.018521801437181334, "n": 5, "N": 5710, "order": 58}, {"M": "2016", "seg1": "Total", "seg2": "Grupo VI", "prop": 0.006860651709866681, "lower": 0.003851024270394597, "upper": 0.01169377486247541, "n": 13, "N": 13553, "order": 59}, {"M": "2016", "seg1": "Total", "seg2": "Grupo VII", "prop": 0.010134780617962837, "lower": 0.005929352911257758, "upper": 0.016224008748517364, "n": 14, "N": 13773, "order": 60}, {"M": "2016", "seg1": "Total", "seg2": "No ha trabajado", "prop": 0.018341356814136393, "lower": 0.011197288661065525, "upper": 0.026931238234614126, "n": 22, "N": 25112, "order": 61}, {"M": "2016", "seg1": "Total", "seg2": "Total", "prop": 0.009943964179673737, "lower": 0.007602557838947161, "upper": 0.012581656465867546, "n": 63, "N": 68786, "order": 62}]}}