{"config": {"view": {"continuousWidth": 300, "continuousHeight": 300}, "locale": {"number": {"decimal": ",", "thousands": ".", "grouping": [3], "currency": ["", "\u00a0\u20ac"]}}, "title": {"dx": 30, "dy": -15, "fontSize": 15}}, "data": {"name": "data-041a94daaa69f6eb2b35647fdfbeb2df"}, "facet": {"column": {"field": "seg2", "header": {"labelFontSize": 15}, "sort": {"field": "order"}, "title": null, "type": "nominal"}, "row": {"field": "row", "header": {"labels": false}, "sort": {"field": "order"}, "title": null, "type": "nominal"}}, "spec": {"layer": [{"mark": {"type": "errorbar", "ticks": {"width": 10}}, "encoding": {"tooltip": {"value": null}, "y": {"axis": {"format": "%", "labelFontSize": 11}, "field": "lower", "title": null, "type": "quantitative"}, "y2": {"field": "upper"}}}, {"mark": {"type": "line", "point": {"size": 50}}, "encoding": {"tooltip": [{"field": "seg1", "title": "Grupo", "type": "nominal"}, {"field": "prop", "format": ".2%", "title": "Estimaci\u00f3n", "type": "quantitative"}, {"field": "lower", "format": ".2%", "title": "L\u00edmite inferior", "type": "quantitative"}, {"field": "upper", "format": ".2%", "title": "L\u00edmite superior", "type": "quantitative"}], "y": {"axis": {"format": "%", "labelFontSize": 11}, "field": "prop", "title": null, "type": "quantitative"}}, "name": "view_177"}], "encoding": {"color": {"field": "seg1", "legend": {"labelFontSize": 12, "symbolSize": 400}, "sort": {"field": "order"}, "title": null, "type": "nominal"}, "x": {"axis": {"labelAngle": 0, "labelFontSize": 11}, "field": "M", "sort": {"field": "order"}, "title": null, "type": "nominal"}, "xOffset": {"field": "seg1", "scale": {"paddingOuter": 0.5}, "sort": {"field": "order"}, "type": "nominal"}}, "height": 175, "width": {"step": 45, "for": "position"}}, "params": [{"name": "param_219", "select": {"type": "interval", "encodings": ["x", "y"]}, "bind": "scales", "views": ["view_177"]}], "resolve": {"axis": {"x": "independent", "y": "independent"}, "scale": {"xOffset": "independent"}}, "title": {"text": ["Hogares con personas con problemas de nervios, depresi\u00f3n o trastorno mental por", "edici\u00f3n, sexo y nivel de estudios (porcentajes e intervalos de confianza al 95%)"], "subtitle": "Fuente: Encuesta Andaluza de Salud (adultos). C\u00f3digo de variable: P2A_ner_R"}, "transform": [{"calculate": "datum.seg1 == 'Total'", "as": "row"}, {"filter": "true == true"}], "$schema": "https://vega.github.io/schema/vega-lite/v5.17.0.json", "datasets": {"data-041a94daaa69f6eb2b35647fdfbeb2df": [{"M": "2007", "seg1": "Hombre", "seg2": "Primarios", "prop": 0.044386226420099754, "lower": 0.033372267699215113, "upper": 0.05836836214042793, "n": 45, "N": 45794, "order": 0}, {"M": "2007", "seg1": "Hombre", "seg2": "Secundarios", "prop": 0.019027706495145433, "lower": 0.013587392169465645, "upper": 0.026411023576298025, "n": 32, "N": 32222, "order": 1}, {"M": "2007", "seg1": "Hombre", "seg2": "Universitarios", "prop": 0.023399365310614952, "lower": 0.013714901069933796, "upper": 0.03858904092141761, "n": 14, "N": 12903, "order": 2}, {"M": "2007", "seg1": "Hombre", "seg2": "Total", "prop": 0.027748339344723177, "lower": 0.02263927214830709, "upper": 0.03349551211709287, "n": 91, "N": 90919, "order": 3}, {"M": "2007", "seg1": "Mujer", "seg2": "Primarios", "prop": 0.06823381533433545, "lower": 0.05588390438236556, "upper": 0.0832791926680112, "n": 87, "N": 89735, "order": 4}, {"M": "2007", "seg1": "Mujer", "seg2": "Secundarios", "prop": 0.03657437486549525, "lower": 0.027765647926342875, "upper": 0.04625385160668004, "n": 56, "N": 58068, "order": 5}, {"M": "2007", "seg1": "Mujer", "seg2": "Universitarios", "prop": 0.015010754301767884, "lower": 0.006397674364733461, "upper": 0.030115989711097323, "n": 7, "N": 7151, "order": 6}, {"M": "2007", "seg1": "Mujer", "seg2": "Total", "prop": 0.04585544588936078, "lower": 0.03846916856404701, "upper": 0.05376112332966161, "n": 150, "N": 154955, "order": 7}, {"M": "2007", "seg1": "Total", "seg2": "Primarios", "prop": 0.05774986686216372, "lower": 0.0484522850809905, "upper": 0.06742558845124336, "n": 132, "N": 135529, "order": 8}, {"M": "2007", "seg1": "Total", "seg2": "Secundarios", "prop": 0.027518302549339683, "lower": 0.022035417350256617, "upper": 0.0340320487066907, "n": 88, "N": 90290, "order": 9}, {"M": "2007", "seg1": "Total", "seg2": "Universitarios", "prop": 0.019511103199593975, "lower": 0.011895164790201635, "upper": 0.029251805492591307, "n": 21, "N": 20054, "order": 10}, {"M": "2007", "seg1": "Total", "seg2": "Total", "prop": 0.03694152896909649, "lower": 0.03244667635858735, "upper": 0.04177405043786457, "n": 241, "N": 245873, "order": 11}, {"M": "2012", "seg1": "Hombre", "seg2": "Primarios", "prop": 0.04505524146523994, "lower": 0.032396297002342915, "upper": 0.06277178588917423, "n": 40, "N": 43913, "order": 12}, {"M": "2012", "seg1": "Hombre", "seg2": "Secundarios", "prop": 0.021614739635586275, "lower": 0.01591642540939716, "upper": 0.029421771799322514, "n": 42, "N": 42450, "order": 13}, {"M": "2012", "seg1": "Hombre", "seg2": "Universitarios", "prop": 0.037042821586716124, "lower": 0.020783234968306533, "upper": 0.056356642343410784, "n": 16, "N": 17824, "order": 14}, {"M": "2012", "seg1": "Hombre", "seg2": "Total", "prop": 0.030466131105195467, "lower": 0.024441635399718824, "upper": 0.0371349778718883, "n": 98, "N": 104188, "order": 15}, {"M": "2012", "seg1": "Mujer", "seg2": "Primarios", "prop": 0.07595063155722181, "lower": 0.06284582633962761, "upper": 0.09239593990945175, "n": 97, "N": 101607, "order": 16}, {"M": "2012", "seg1": "Mujer", "seg2": "Secundarios", "prop": 0.03333651103057679, "lower": 0.025133230058100225, "upper": 0.042277113869993437, "n": 56, "N": 58599, "order": 17}, {"M": "2012", "seg1": "Mujer", "seg2": "Universitarios", "prop": 0.031068124839888227, "lower": 0.01548005358243119, "upper": 0.05083166946699847, "n": 13, "N": 14249, "order": 18}, {"M": "2012", "seg1": "Mujer", "seg2": "Total", "prop": 0.04908356911839328, "lower": 0.04228741832190022, "upper": 0.057089104807943845, "n": 166, "N": 174454, "order": 19}, {"M": "2012", "seg1": "Total", "seg2": "Primarios", "prop": 0.06292889616945081, "lower": 0.05420110656264119, "upper": 0.07368552668888101, "n": 137, "N": 145519, "order": 20}, {"M": "2012", "seg1": "Total", "seg2": "Secundarios", "prop": 0.027150980706260555, "lower": 0.02260670960779881, "upper": 0.032867537273000305, "n": 98, "N": 101049, "order": 21}, {"M": "2012", "seg1": "Total", "seg2": "Universitarios", "prop": 0.034127153202324435, "lower": 0.02354843135769099, "upper": 0.050042049125445985, "n": 29, "N": 32073, "order": 22}, {"M": "2012", "seg1": "Total", "seg2": "Total", "prop": 0.03995430817922091, "lower": 0.035330876034705326, "upper": 0.045048695606724344, "n": 264, "N": 278642, "order": 23}, {"M": "2016", "seg1": "Hombre", "seg2": "Primarios", "prop": 0.07768268314194024, "lower": 0.060922776176161854, "upper": 0.09905620443581915, "n": 59, "N": 58600, "order": 24}, {"M": "2016", "seg1": "Hombre", "seg2": "Secundarios", "prop": 0.03761035631768111, "lower": 0.03002024621700212, "upper": 0.04677274533364326, "n": 76, "N": 78094, "order": 25}, {"M": "2016", "seg1": "Hombre", "seg2": "Universitarios", "prop": 0.030134650854865278, "lower": 0.01803163587088283, "upper": 0.0514813471413326, "n": 14, "N": 16480, "order": 26}, {"M": "2016", "seg1": "Hombre", "seg2": "Total", "prop": 0.0453495592772059, "lower": 0.03795664646956942, "upper": 0.05316885924305042, "n": 149, "N": 153173, "order": 27}, {"M": "2016", "seg1": "Mujer", "seg2": "Primarios", "prop": 0.18552409372333267, "lower": 0.16114423906065786, "upper": 0.21196555663624303, "n": 165, "N": 184533, "order": 28}, {"M": "2016", "seg1": "Mujer", "seg2": "Secundarios", "prop": 0.09015108085208534, "lower": 0.07734009145572698, "upper": 0.10430258145425496, "n": 167, "N": 179247, "order": 29}, {"M": "2016", "seg1": "Mujer", "seg2": "Universitarios", "prop": 0.044822430804935885, "lower": 0.028072928651290883, "upper": 0.06559280486190074, "n": 22, "N": 24614, "order": 30}, {"M": "2016", "seg1": "Mujer", "seg2": "Total", "prop": 0.10996137371369608, "lower": 0.09908274263481157, "upper": 0.12126241740967718, "n": 354, "N": 388395, "order": 31}, {"M": "2016", "seg1": "Total", "seg2": "Primarios", "prop": 0.13901208840540086, "lower": 0.12228050215907038, "upper": 0.15686455151531167, "n": 224, "N": 243133, "order": 32}, {"M": "2016", "seg1": "Total", "seg2": "Secundarios", "prop": 0.06331141930729252, "lower": 0.05619269730352026, "upper": 0.07181633789144826, "n": 243, "N": 257341, "order": 33}, {"M": "2016", "seg1": "Total", "seg2": "Universitarios", "prop": 0.03749364464230744, "lower": 0.026979435525694945, "upper": 0.050696701650566105, "n": 36, "N": 41094, "order": 34}, {"M": "2016", "seg1": "Total", "seg2": "Total", "prop": 0.07837773933150513, "lower": 0.07166119758205028, "upper": 0.0850528849121471, "n": 503, "N": 541568, "order": 35}, {"M": "2023", "seg1": "Hombre", "seg2": "Primarios", "prop": 0.04953896753085551, "lower": 0.03435609888638584, "upper": 0.07126420574583482, "n": 33, "N": 28660, "order": 36}, {"M": "2023", "seg1": "Hombre", "seg2": "Secundarios", "prop": 0.03306857777379781, "lower": 0.02539196337799906, "upper": 0.042559661758895875, "n": 68, "N": 73762, "order": 37}, {"M": "2023", "seg1": "Hombre", "seg2": "Universitarios", "prop": 0.025713467676645282, "lower": 0.015037605793985389, "upper": 0.04063586813453784, "n": 17, "N": 18297, "order": 38}, {"M": "2023", "seg1": "Hombre", "seg2": "Total", "prop": 0.03428845590062775, "lower": 0.028674277117636298, "upper": 0.04187634387336513, "n": 118, "N": 120719, "order": 39}, {"M": "2023", "seg1": "Mujer", "seg2": "Primarios", "prop": 0.07655448831899846, "lower": 0.06352133842322867, "upper": 0.09230242902344735, "n": 105, "N": 62931, "order": 40}, {"M": "2023", "seg1": "Mujer", "seg2": "Secundarios", "prop": 0.04399656826251444, "lower": 0.03669327529771606, "upper": 0.05277637514165389, "n": 133, "N": 95534, "order": 41}, {"M": "2023", "seg1": "Mujer", "seg2": "Universitarios", "prop": 0.028025013793451927, "lower": 0.018370846209994497, "upper": 0.0409534116090418, "n": 27, "N": 20595, "order": 42}, {"M": "2023", "seg1": "Mujer", "seg2": "Total", "prop": 0.04802700603832935, "lower": 0.042052426069961915, "upper": 0.05476098379433832, "n": 265, "N": 179059, "order": 43}, {"M": "2023", "seg1": "Total", "seg2": "Primarios", "prop": 0.06539524331256329, "lower": 0.05606083940806136, "upper": 0.07765429893472563, "n": 138, "N": 91590, "order": 44}, {"M": "2023", "seg1": "Total", "seg2": "Secundarios", "prop": 0.03845912215105986, "lower": 0.032818909507556386, "upper": 0.045048768574719594, "n": 201, "N": 169295, "order": 45}, {"M": "2023", "seg1": "Total", "seg2": "Universitarios", "prop": 0.026887850418689418, "lower": 0.01980221862035832, "upper": 0.03734580790200394, "n": 44, "N": 38892, "order": 46}, {"M": "2023", "seg1": "Total", "seg2": "Total", "prop": 0.04135447970977614, "lower": 0.03733610127374179, "upper": 0.04623588255937143, "n": 383, "N": 299778, "order": 47}]}}